cuplegend/__init__.py
cuplegend/main.py
cuplegend/methods/__init__.py
cuplegend/methods/app.py
cuplegend/methods/base.py
cuplegend/methods/blockchain.py
cuplegend/methods/checks.py
cuplegend/methods/info.py
cuplegend/methods/invoices.py
cuplegend/types/__init__.py
cuplegend/types/base_types.py
cuplegend/types/methods_types.py
cuplegend-1.0.0.dist-info/METADATA
cuplegend-1.0.0.dist-info/WHEEL
cuplegend-1.0.0.dist-info/licenses/LICENSE
cuplegend-1.0.0.dist-info/RECORD
