Metadata-Version: 2.4
Name: cuplegend
Version: 1.0.0
Summary: Библиотека для упрощённой работы с Cup Legend API.
Project-URL: GitHub, https://github.com/aiocringe/CupLegend
Project-URL: API, https://api.cuplegend.ru/docs
Project-URL: Telegram, https://t.me/CupLegend
Author-email: aiocringe <aiocringe@hotmail.com>
License-File: LICENSE
Classifier: License :: OSI Approved :: MIT License
Classifier: Operating System :: OS Independent
Classifier: Programming Language :: Python :: 3
Requires-Python: >=3.8.0
Requires-Dist: pydantic>=2.0.0
Requires-Dist: requests>=2.0.0
